Metadata-Version: 2.1
Name: ftpc
Version: 0.0.4
Summary: Develop ftpc
Home-page: UNKNOWN
Author: Baxromov
License: UNKNOWN
Platform: UNKNOWN
Classifier: Programming Language :: Python :: 3
Classifier: License :: OSI Approved :: MIT License
Classifier: Operating System :: OS Independent
Requires-Python: >=3.6
